gherkin2oas/__init__.py
gherkin2oas/gherkin2oas.py
gherkin2oas/utils/__init__.py
gherkin2oas/utils/formatter.py
gherkin2oas/utils/nlp.py
gherkin2oas/utils/preprocessor.py
gherkin2oas-1.0.1.dist-info/LICENSE
gherkin2oas-1.0.1.dist-info/METADATA
gherkin2oas-1.0.1.dist-info/WHEEL
gherkin2oas-1.0.1.dist-info/top_level.txt
gherkin2oas-1.0.1.dist-info/RECORD
