Metadata-Version: 2.1
Name: gherkin2oas
Version: 1.0.1
Summary: A converter from Gherkin to OAS
Home-page: https://github.com/TasosDhm/gherkin2oas
Author: Tasos Dimanidis
Author-email: dhmtasos@gmail.com
License: UNKNOWN
Platform: UNKNOWN
Classifier: Programming Language :: Python :: 3
Classifier: License :: OSI Approved :: GNU Lesser General Public License v3 (LGPLv3)
Classifier: Operating System :: OS Independent
Requires-Python: >=3
Requires-Dist: nltk
Requires-Dist: TextBlob
Requires-Dist: inflect
Requires-Dist: python-dateutil
Requires-Dist: gherkin-official (>=4.1.3)
Requires-Dist: openapi-spec-validator
